hack-mentor/__init__.py
hack-mentor/main.py
hack_mentor/__init__.py
hack_mentor/main.py
hack_mentor/prompts.py
hack_mentor-0.7.dist-info/METADATA
hack_mentor-0.7.dist-info/WHEEL
hack_mentor-0.7.dist-info/entry_points.txt
hack_mentor-0.7.dist-info/top_level.txt
hack_mentor-0.7.dist-info/RECORD
