Metadata-Version: 2.1
Name: hack-mentor
Version: 0.7
Summary: GPT4 in your terminal, watching you code and giving feedback
Author-email: George Pickett <gpickett00@gmail.com>
Project-URL: Homepage, https://github.com/grp06/hack_mentor
Project-URL: Bug Tracker, https://github.com/grp06/hack_mentor/issues
Classifier: Programming Language :: Python :: 3
Classifier: License :: OSI Approved :: MIT License
Classifier: Operating System :: OS Independent
Requires-Python: >=3.7
Requires-Dist: langchain
Requires-Dist: flask
Requires-Dist: python-dotenv
Requires-Dist: rich
Requires-Dist: openai
